flake8_implicit_str_concat.py
flake8_implicit_str_concat-0.5.0.dist-info/METADATA
flake8_implicit_str_concat-0.5.0.dist-info/WHEEL
flake8_implicit_str_concat-0.5.0.dist-info/entry_points.txt
flake8_implicit_str_concat-0.5.0.dist-info/licenses/LICENSE
flake8_implicit_str_concat-0.5.0.dist-info/RECORD
