Metadata-Version: 2.3
Name: flake8-implicit-str-concat
Version: 0.5.0
Summary: Flake8 plugin to encourage correct string literal concatenation
Project-URL: Homepage, https://github.com/flake8-implicit-str-concat/flake8-implicit-str-concat
Author-email: Dylan Turner <58230987+keisheiled@users.noreply.github.com>
License: MIT
License-File: LICENSE
Classifier: Development Status :: 5 - Production/Stable
Classifier: Environment :: Console
Classifier: Framework :: Flake8
Classifier: Intended Audience :: Developers
Classifier: License :: OSI Approved :: MIT License
Classifier: Operating System :: OS Independent
Classifier: Programming Language :: Python
Classifier: Programming Language :: Python :: 3 :: Only
Classifier: Programming Language :: Python :: 3.9
Classifier: Programming Language :: Python :: 3.10
Classifier: Programming Language :: Python :: 3.11
Classifier: Programming Language :: Python :: 3.12
Classifier: Programming Language :: Python :: 3.13
Classifier: Topic :: Software Development :: Libraries :: Python Modules
Classifier: Topic :: Software Development :: Quality Assurance
Requires-Python: >=3.9
Requires-Dist: more-itertools>=8.0.2; python_version <= '3.9'
